mcir/__init__.py
mcir/t1_calc.py
mcir-0.0.1.dist-info/METADATA
mcir-0.0.1.dist-info/RECORD
mcir-0.0.1.dist-info/WHEEL
mcir-0.0.1.dist-info/top_level.txt
