Metadata-Version: 2.1
Name: mcir
Version: 0.0.1
Summary: A package for performing multi-component inversion recovery (IR) analysis of microstructural laminar patterns of the cortex.
Home-page: https://github.com/omritomer/mcir
Author: Omri Tomer
Author-email: omritomer1@mail.tau.ac.il
License: MIT license
Keywords: mcir
Platform: UNKNOWN
Classifier: Development Status :: 2 - Pre-Alpha
Classifier: Intended Audience :: Developers
Classifier: License :: OSI Approved :: MIT License
Classifier: Natural Language :: English
Classifier: Programming Language :: Python :: 2
Classifier: Programming Language :: Python :: 2.7
Classifier: Programming Language :: Python :: 3
Classifier: Programming Language :: Python :: 3.5
Classifier: Programming Language :: Python :: 3.6
Classifier: Programming Language :: Python :: 3.7
Classifier: Programming Language :: Python :: 3.8
Requires-Python: >=2.7, !=3.0.*, !=3.1.*, !=3.2.*, !=3.3.*, !=3.4.*
